cimgraph/__init__.py
cimgraph/data_profile/__init__.py
cimgraph/data_profile/cimhub_2023/__init__.py
cimgraph/data_profile/cimhub_2023/cimhub_2023.rdfs
cimgraph/data_profile/cimhub_2023/cimhub_profile_2023.py
cimgraph/data_profile/known_problem_classes.py
cimgraph/data_profile/rc4_2021/__init__.py
cimgraph/data_profile/rc4_2021/gridappsd_cim_profile_rc4_2021.py
cimgraph/data_profile/rc4_2021/rc4_2021.rdfs
cimgraph/databases/__init__.py
cimgraph/databases/blazegraph/__init__.py
cimgraph/databases/blazegraph/blazegraph.py
cimgraph/databases/fileparsers/__init__.py
cimgraph/databases/fileparsers/xml_parser.py
cimgraph/databases/graphdb/__init__.py
cimgraph/databases/graphdb/graphdb.py
cimgraph/databases/gridappsd/__init__.py
cimgraph/databases/gridappsd/gridappsd.py
cimgraph/databases/mysql/__init__.py
cimgraph/databases/mysql/mysql.py
cimgraph/databases/neo4j/__init__.py
cimgraph/databases/neo4j/neo4j.py
cimgraph/databases/piwebapi/__init__.py
cimgraph/databases/rdflib/__init__.py
cimgraph/databases/rdflib/rdflib.py
cimgraph/models/.ipynb_checkpoints/Untitled-checkpoint.ipynb
cimgraph/models/__init__.py
cimgraph/models/bus_branch_model.py
cimgraph/models/distributed_area.py
cimgraph/models/feeder_model.py
cimgraph/models/graph_model.py
cimgraph/models/node_breaker_model.py
cimgraph/queries/__init__.py
cimgraph/queries/cypher/__init__.py
cimgraph/queries/cypher/get_all_edges.py
cimgraph/queries/cypher/get_all_nodes.py
cimgraph/queries/jsonld_sql/__init__.py
cimgraph/queries/jsonld_sql/get_all_edges.py
cimgraph/queries/jsonld_sql/get_all_nodes.py
cimgraph/queries/ontotext/__init__.py
cimgraph/queries/ontotext/get_all_edges.py
cimgraph/queries/ontotext/get_all_nodes.py
cimgraph/queries/rdflib/__init__.py
cimgraph/queries/rdflib/get_all_edges.py
cimgraph/queries/rdflib/get_all_nodes.py
cimgraph/queries/sparql/__init__.py
cimgraph/queries/sparql/get_all_edges.py
cimgraph/queries/sparql/get_all_nodes.py
cimgraph/queries/sparql/upload_triples.py
cimgraph/utils/__init__.py
cim_graph-2023.8.1a1.dist-info/LICENSE
cim_graph-2023.8.1a1.dist-info/METADATA
cim_graph-2023.8.1a1.dist-info/WHEEL
cim_graph-2023.8.1a1.dist-info/RECORD
