Metadata-Version: 2.1
Name: cim-graph
Version: 2023.8.1a1
Summary: CIM Graph
Author: A. Anderson
Author-email: 19935503+AAndersn@users.noreply.github.com
Requires-Python: >=3.8.1,<4.0
Classifier: Programming Language :: Python :: 3
Classifier: Programming Language :: Python :: 3.9
Classifier: Programming Language :: Python :: 3.10
Classifier: Programming Language :: Python :: 3.11
Classifier: Programming Language :: Python :: 3.12
Provides-Extra: all
Provides-Extra: gridappsd
Requires-Dist: SPARQLWrapper (>=2.0.0,<3.0.0)
Requires-Dist: gridappsd-python (>=2023.9.1,<2024.0.0) ; extra == "gridappsd" or extra == "all"
Requires-Dist: mysql-connector-python (>=8.0.0,<9.0.0)
Requires-Dist: neo4j (>=5.10.0,<6.0.0) ; extra == "all"
Requires-Dist: nest-asyncio (>=1.5.8,<2.0.0)
Requires-Dist: oxrdflib (>=0.3.6,<0.4.0)
Requires-Dist: rdflib (>=7.0.0,<8.0.0)
Requires-Dist: rdflib-neo4j (>=0.0.1b6,<0.0.2)
Requires-Dist: xsdata (>=22.5,<23.0)
